mhs2300a.py
mhs2300a-0.0.5.dist-info/METADATA
mhs2300a-0.0.5.dist-info/WHEEL
mhs2300a-0.0.5.dist-info/top_level.txt
mhs2300a-0.0.5.dist-info/RECORD
