Metadata-Version: 2.1
Name: mhs2300a
Version: 0.0.5
Summary: Python module for controlling inexpensive MHS-2300A signal generators
Home-page: UNKNOWN
Author: Ferrer, Manuel
Author-email: UNKNOWN
License: UNKNOWN
Platform: UNKNOWN
Classifier: Development Status :: 3 - Alpha
Classifier: Intended Audience :: Education
Classifier: Programming Language :: Python :: 3
Classifier: Operating System :: MacOS :: MacOS X
Classifier: Operating System :: Microsoft :: Windows
Requires-Dist: pyserial (>=3.5)
Requires-Dist: cached-property (>=1.5.2)
